boostsrl/__init__.py
boostsrl/_meta.py
boostsrl/auc.jar
boostsrl/background.py
boostsrl/base.py
boostsrl/boostsrl.py
boostsrl/database.py
boostsrl/example_data.py
boostsrl/mln.py
boostsrl/rdn.py
boostsrl/system_manager.py
boostsrl/v1-0.jar
boostsrl/tests/__init__.py
boostsrl/tests/test_background.py
boostsrl/tests/test_base.py
boostsrl/tests/test_database.py
boostsrl/tests/test_mln.py
boostsrl/tests/test_rdn.py
boostsrl/tests/test_system_manager.py
boostsrl/tests/test_system_manager_reset.py
boostsrl/utils/__init__.py
boostsrl/utils/_show_versions.py
boostsrl/utils/tests/__init__.py
boostsrl/utils/tests/test_show_versions.py
boostsrl-0.4.3.dist-info/LICENSE
boostsrl-0.4.3.dist-info/METADATA
boostsrl-0.4.3.dist-info/WHEEL
boostsrl-0.4.3.dist-info/top_level.txt
boostsrl-0.4.3.dist-info/RECORD
