Metadata-Version: 2.1
Name: boostsrl
Version: 0.4.3
Summary: Python wrappers for using BoostSRL jar files.
Home-page: https://starling.utdallas.edu/software/boostsrl-python-wrappers/
Author: Alexander L. Hayes (hayesall)
Author-email: alexander@batflyer.net
License: GPL-3.0
Download-URL: https://github.com/starling-lab/boostsrl-python-package
Keywords: machine-learning-algorithms machine-learning statistical-learning pattern-classification artificial-intelligence
Platform: UNKNOWN
Classifier: Development Status :: 3 - Alpha
Classifier: Intended Audience :: Education
Classifier: Intended Audience :: Science/Research
Classifier: License :: OSI Approved :: GNU General Public License v3 (GPLv3)
Classifier: Operating System :: POSIX :: Linux
Classifier: Programming Language :: Python :: 3.6
Classifier: Programming Language :: Python :: 3.7
Classifier: Topic :: Scientific/Engineering :: Artificial Intelligence
Requires-Dist: graphviz
Requires-Dist: numpy
Requires-Dist: scipy
Requires-Dist: scikit-learn
Provides-Extra: docs
Requires-Dist: sphinx ; extra == 'docs'
Requires-Dist: sphinx-rtd-theme ; extra == 'docs'
Requires-Dist: sphinx-gallery ; extra == 'docs'
Requires-Dist: numpydoc ; extra == 'docs'
Requires-Dist: matplotlib ; extra == 'docs'
Provides-Extra: tests
Requires-Dist: coverage ; extra == 'tests'
Requires-Dist: pytest ; extra == 'tests'
